odoo/addons/stock_average_daily_sale/README.rst
odoo/addons/stock_average_daily_sale/__init__.py
odoo/addons/stock_average_daily_sale/__manifest__.py
odoo/addons/stock_average_daily_sale/data/ir_cron.xml
odoo/addons/stock_average_daily_sale/demo/stock_average_daily_sale_config.xml
odoo/addons/stock_average_daily_sale/demo/stock_move.xml
odoo/addons/stock_average_daily_sale/i18n/it.po
odoo/addons/stock_average_daily_sale/i18n/stock_average_daily_sale.pot
odoo/addons/stock_average_daily_sale/models/__init__.py
odoo/addons/stock_average_daily_sale/models/stock_average_daily_sale.py
odoo/addons/stock_average_daily_sale/models/stock_average_daily_sale_config.py
odoo/addons/stock_average_daily_sale/models/stock_warehouse.py
odoo/addons/stock_average_daily_sale/readme/CONFIGURE.rst
odoo/addons/stock_average_daily_sale/readme/CONTRIBUTORS.rst
odoo/addons/stock_average_daily_sale/readme/DESCRIPTION.rst
odoo/addons/stock_average_daily_sale/readme/HISTORY.rst
odoo/addons/stock_average_daily_sale/readme/ROADMAP.rst
odoo/addons/stock_average_daily_sale/security/stock_average_daily_sale.xml
odoo/addons/stock_average_daily_sale/security/stock_average_daily_sale_config.xml
odoo/addons/stock_average_daily_sale/security/stock_average_daily_sale_demo.xml
odoo/addons/stock_average_daily_sale/static/description/icon.png
odoo/addons/stock_average_daily_sale/static/description/index.html
odoo/addons/stock_average_daily_sale/tests/__init__.py
odoo/addons/stock_average_daily_sale/tests/common.py
odoo/addons/stock_average_daily_sale/tests/test_average_daily_sale.py
odoo/addons/stock_average_daily_sale/views/stock_average_daily_sale.xml
odoo/addons/stock_average_daily_sale/views/stock_average_daily_sale_config.xml
odoo/addons/stock_average_daily_sale/views/stock_warehouse.xml
odoo/addons/stock_average_daily_sale/wizards/__init__.py
odoo/addons/stock_average_daily_sale/wizards/stock_average_daily_sale_demo.py
odoo14_addon_stock_average_daily_sale-14.0.1.0.2.dist-info/METADATA
odoo14_addon_stock_average_daily_sale-14.0.1.0.2.dist-info/WHEEL
odoo14_addon_stock_average_daily_sale-14.0.1.0.2.dist-info/top_level.txt
odoo14_addon_stock_average_daily_sale-14.0.1.0.2.dist-info/RECORD
