Metadata-Version: 2.1
Name: odoo14-addon-stock_average_daily_sale
Version: 14.0.1.0.2
Summary: Allows to gather delivered products average on daily basis
Home-page: https://github.com/OCA/stock-logistics-reporting
Author: ACSONE SA/NV,BCIM,Odoo Community Association (OCA)
Author-email: support@odoo-community.org
License: AGPL-3
Classifier: Programming Language :: Python
Classifier: Framework :: Odoo
Classifier: Framework :: Odoo :: 14.0
Classifier: License :: OSI Approved :: GNU Affero General Public License v3
Requires-Python: >=3.6
Requires-Dist: freezegun
Requires-Dist: odoo14-addon-product-route-mto
Requires-Dist: odoo14-addon-stock-location-warehouse
Requires-Dist: odoo14-addon-stock-storage-type-putaway-abc
Requires-Dist: odoo<14.1dev,>=14.0a
